{"source_text": "\u0e99\u0ec9\u0ead\u0e87\u0ec0\u0e8a\u0eb7\u0ec8\u0ead\u0ea7\u0ec8\u0eb2\u0edc\u0eb7\u0ec8\u0e87\u0eaa\u0eb0\u0e9e\u0eb2\u0e9a\u0ec1\u0ea7\u0e94\u0ea5\u0ec9\u0ead\u0ea1\u0e94\u0ec9\u0eb2\u0e99\u0e81\u0eb2\u0e99\u0eaa\u0eb6\u0e81\u0eaa\u0eb2\u0e97\u0eb5\u0ec8 \u0ec0\u0edd\u0eb2\u0eb0\u0e95\u0ec9\u0ead\u0e87\u0ec1\u0ea1\u0ec8\u0e99\u0eaa\u0eb0\u0e9e\u0eb2\u0e9a\u0ec1\u0ea7\u0e94\u0ea5\u0ec9\u0ead\u0ea1\u0e97\u0eb5\u0ec8\u0eaa\u0eb2\u0ea1\u0eb2\u0e94\u0e8a\u0eb8\u0e81\u0e8d\u0eb9\u0ec9\u0e84\u0ea7\u0eb2\u0ea1\u0ea2\u0eb2\u0e81\u0eae\u0eb9\u0ec9\u0ea2\u0eb2\u0e81\u0ec0\u0eab\u0eb1\u0e99\u0ec1\u0ea5\u0eb0\u0e84\u0ea7\u0eb2\u0ea1\u0e84\u0eb4\u0e94\u0eaa\u0ec9\u0eb2\u0e87\u0eaa\u0eb1\u0e99.", "source_lang": "lo", "target_text": "Em tin r\u1eb1ng m\u1ed9t m\u00f4i tr\u01b0\u1eddng gi\u00e1o d\u1ee5c ph\u00f9 h\u1ee3p ph\u1ea3i l\u00e0 m\u1ed9t m\u00f4i tr\u01b0\u1eddng c\u00f3 th\u1ec3 th\u00fac \u0111\u1ea9y s\u1ef1 t\u00f2 m\u00f2 v\u00e0 s\u00e1ng t\u1ea1o.\n", "target_lang": "vi", "task_name": "public_plain_text_translation", "status": "translated", "message": "", "schema_version": 1}