{"source_text": "\u0ec3\u0e99\u0ec4\u0ea5\u0e8d\u0eb0\u0e97\u0eb5\u0ec8\u0eaa\u0eb1\u0e9a\u0eaa\u0ebb\u0e99\u0e82\u0ead\u0e87\u0e81\u0eb2\u0e99\u0ea5\u0eb0\u0e9a\u0eb2\u0e94\u0e82\u0ead\u0e87\u0e9e\u0eb0\u0e8d\u0eb2\u0e94\u0ec2\u0e84\u0ea7\u0eb4\u0e94-19, \u0e99\u0eb1\u0e81\u0e97\u0ec8\u0ead\u0e87\u0e97\u0ec8\u0ebd\u0ea7\u0eab\u0ebc\u0eb2\u0e8d\u0e84\u0ebb\u0e99\u0ea1\u0eb1\u0e81\u0ec1\u0e95\u0ec8\u0e87\u0e81\u0eb4\u0e99\u0ea2\u0eb9\u0ec8\u0ec0\u0eae\u0eb7\u0ead\u0e99\u0e9e\u0eb1\u0e81\u0ec1\u0e97\u0e99\u0e97\u0eb5\u0ec8\u0e88\u0eb0\u0ec4\u0e9b\u0eae\u0ec9\u0eb2\u0e99", "source_lang": "lo", "target_text": "Trong th\u1eddi gian di\u1ec5n bi\u1ebfn ph\u1ee9c t\u1ea1p c\u1ee7a d\u1ecbch Covid-19, nhi\u1ec1u du kh\u00e1ch th\u01b0\u1eddng n\u1ea5u \u0103n t\u1ea1i nh\u00e0 ngh\u1ec9 thay v\u00ec \u0111\u1ebfn c\u1eeda h\u00e0ng.\n", "target_lang": "vi", "task_name": "public_plain_text_translation", "status": "translated", "message": "", "schema_version": 1}