{"source_text": "\u0ec3\u0e99\u0ec0\u0ea7\u0ea5\u0eb2\u0e94\u0ebd\u0ea7\u0e81\u0eb1\u0e99\u0e99\u0eb1\u0ec9\u0e99, \u0eaa\u0ead\u0e87\u0e9b\u0eb0\u0ec0\u0e97\u0e94\u0ea1\u0eb5(\u0ea1\u0eb5\u0e84\u0ea7\u0eb2\u0ea1\u0eaa\u0eb2\u0ea1\u0eb2\u0e94\u0e9a\u0ebb\u0ec8\u0ea1\u0e8a\u0ec9\u0ead\u0e99)\u0e97\u0ec8\u0eb2\u0ec1\u0eae\u0e87\u0ead\u0eb1\u0e99\u0ec3\u0eab\u0e8d\u0ec8\u0eab\u0ebc\u0ea7\u0e87\u0ec0\u0e9e\u0eb7\u0ec8\u0ead\u0eaa\u0eb7\u0e9a\u0e95\u0ecd\u0ec8\u0e82\u0eb0\u0eab\u0e8d\u0eb2\u0e8d\u0e81\u0eb2\u0e99\u0eae\u0ec8\u0ea7\u0ea1\u0ea1\u0eb7\u0ec3\u0e99\u0e82\u0ebb\u0e87\u0ec0\u0e82\u0e94.", "source_lang": "lo", "target_text": "\u0110\u1ed3ng th\u1eddi, hai n\u01b0\u1edbc c\u00f3 (ti\u1ec1m n\u0103ng) ti\u1ec1m n\u0103ng to l\u1edbn \u0111\u1ec3 ti\u1ebfp t\u1ee5c m\u1edf r\u1ed9ng h\u1ee3p t\u00e1c trong l\u0129nh v\u1ef1c.\n", "target_lang": "vi", "task_name": "public_plain_text_translation", "status": "translated", "message": "", "schema_version": 1}